AUTHORS
CHANGELOG.txt
DESCRIPTION
LICENSE
MANIFEST.in
README.rst
setup.cfg
setup.py
copywriting/__init__.py
copywriting/admin.py
copywriting/context_processors.py
copywriting/feed.py
copywriting/helperFunctions.py
copywriting/models.py
copywriting/signals.py
copywriting/sitemaps.py
copywriting/tests.py
copywriting/urls.py
copywriting/views.py
copywriting/templates/copywriting/copywritingArticle.html
copywriting/templates/copywriting/copywritingIndex.html
copywriting/templatetags/__init__.py
copywriting/templatetags/blogtags.py
django_copywriting.egg-info/PKG-INFO
django_copywriting.egg-info/SOURCES.txt
django_copywriting.egg-info/dependency_links.txt
django_copywriting.egg-info/requires.txt
django_copywriting.egg-info/top_level.txt