Metadata-Version: 1.0
Name: django-copywriting
Version: 0.1.12
Summary: Copywriting is the act of writing copy (text) for the purpose of advertising or marketing a product, business, person, opinion or idea. The addressee (reader, listener, etc.) of the copy is meant to be persuaded to buy the product advertised for, or subscribe to the viewpoint the text shares.
